hikvision/__init__.py
hikvision/api.py
hikvision/constants.py
hikvision/error.py
hikvision-2.0.4.dist-info/LICENSE
hikvision-2.0.4.dist-info/METADATA
hikvision-2.0.4.dist-info/WHEEL
hikvision-2.0.4.dist-info/top_level.txt
hikvision-2.0.4.dist-info/RECORD
