Metadata-Version: 2.1
Name: hikvision
Version: 2.0.4
Summary: Provides a python interface to interact with a hikvision camera
Home-page: https://github.com/fbradyirl/hikvision
Author: Finbarr Brady
Author-email: fbradyirl@github.io
License: MIT
Keywords: hikvision camera python cgi interface
Platform: UNKNOWN
Classifier: Development Status :: 2 - Pre-Alpha
Classifier: Intended Audience :: Developers
Classifier: License :: OSI Approved :: Apache Software License
Classifier: Natural Language :: English
Classifier: Programming Language :: Python :: 3.7
Requires-Dist: requests (>=2.21.0)
